{
  "name": "Themixir Purple Deep",
  "type": "dark",
  "colors": {
    "editor.background": "#1C1231",
    "editor.foreground": "#DCCEFC",
    "editor.selectionBackground": "#8B5CF680",
    "editor.lineHighlightBackground": "#19102C",
    "editorCursor.foreground": "#8B5CF6",
    "editorWhitespace.foreground": "#6F4AC540",
    "editorIndentGuide.background": "#6F4AC520",
    "editorIndentGuide.activeBackground": "#8B5CF660",
    "activityBar.background": "#1C1231",
    "activityBar.foreground": "#DCCEFC",
    "activityBar.inactiveForeground": "#DCCEFC60",
    "activityBarBadge.background": "#8B5CF6",
    "activityBarBadge.foreground": "#1C1231",
    "sideBar.background": "#19102C",
    "sideBar.foreground": "#DCCEFC",
    "sideBarSectionHeader.background": "#1C1231",
    "statusBar.background": "#8B5CF6",
    "statusBar.foreground": "#1C1231",
    "statusBar.noFolderBackground": "#8B5CF6",
    "titleBar.activeBackground": "#1C1231",
    "titleBar.activeForeground": "#DCCEFC",
    "tab.activeBackground": "#1C1231",
    "tab.activeForeground": "#DCCEFC",
    "tab.inactiveBackground": "#19102C",
    "tab.inactiveForeground": "#DCCEFC80",
    "terminal.background": "#1C1231",
    "terminal.foreground": "#DCCEFC"
  },
  "tokenColors": [
    {
      "scope": "comment",
      "settings": {
        "foreground": "#6F4AC5"
      }
    },
    {
      "scope": "string",
      "settings": {
        "foreground": "#8B5CF6"
      }
    },
    {
      "scope": "constant.numeric",
      "settings": {
        "foreground": "#8B5CF6"
      }
    },
    {
      "scope": "keyword",
      "settings": {
        "foreground": "#8B5CF6",
        "fontStyle": "bold"
      }
    },
    {
      "scope": "storage",
      "settings": {
        "foreground": "#8B5CF6"
      }
    },
    {
      "scope": "entity.name.function",
      "settings": {
        "foreground": "#8B5CF6"
      }
    },
    {
      "scope": "variable",
      "settings": {
        "foreground": "#DCCEFC"
      }
    },
    {
      "scope": "punctuation",
      "settings": {
        "foreground": "#DCCEFCB0"
      }
    }
  ]
}